{
  "year": 2026,
  "batch": "本科批",
  "group": "物理类",
  "entries": [
    {
      "index": 17354,
      "universityCode": "2172",
      "universityName": "江苏科技大学苏州理工学院(张家港市)[独立学院]",
      "majorCode": "04",
      "majorName": "数字经济",
      "majorNote": "",
      "subjectRequirement": "不限",
      "planCount": 1,
      "duration": 4,
      "tuition": 18000
    },
    {
      "index": 17355,
      "universityCode": "2172",
      "universityName": "江苏科技大学苏州理工学院(张家港市)[独立学院]",
      "majorCode": "05",
      "majorName": "新能源材料与器件",
      "majorNote": "",
      "subjectRequirement": "化学",
      "planCount": 2,
      "duration": 4,
      "tuition": 20000
    },
    {
      "index": 17356,
      "universityCode": "2172",
      "universityName": "江苏科技大学苏州理工学院(张家港市)[独立学院]",
      "majorCode": "06",
      "majorName": "能源与动力工程",
      "majorNote": "",
      "subjectRequirement": "化学",
      "planCount": 1,
      "duration": 4,
      "tuition": 20000
    },
    {
      "index": 17357,
      "universityCode": "2172",
      "universityName": "江苏科技大学苏州理工学院(张家港市)[独立学院]",
      "majorCode": "07",
      "majorName": "电子信息工程",
      "majorNote": "",
      "subjectRequirement": "化学",
      "planCount": 1,
      "duration": 4,
      "tuition": 20000
    },
    {
      "index": 17358,
      "universityCode": "2172",
      "universityName": "江苏科技大学苏州理工学院(张家港市)[独立学院]",
      "majorCode": "08",
      "majorName": "工程造价",
      "majorNote": "",
      "subjectRequirement": "不限",
      "planCount": 2,
      "duration": 4,
      "tuition": 20000
    }
  ],
  "meta": {
    "year": 2026,
    "batch": "本科批",
    "group": "物理类",
    "source": "河北省教育考试院",
    "sourceUrl": "https://gk.hebeea.edu.cn:88/xxcx/xxcxzx/zsjhIframe",
    "publishedAt": "2026-06-25",
    "quality": "official",
    "updatedAt": "2026-06-25T10:49:24.249Z",
    "totalEntries": 20842,
    "totalPlans": 206906,
    "universityCount": 1263
  }
}