{
  "year": 2025,
  "batch": "本科提前批B段",
  "group": "物理类",
  "entries": [
    {
      "universityCode": "0305",
      "universityName": "电子科技大学(国家专项计划)[公办]",
      "majorGroup": "电子信息类(信息与通信)",
      "planCount": 0,
      "minScore": 657,
      "minRank": 2081,
      "avgScore": 657
    },
    {
      "universityCode": "0305",
      "universityName": "电子科技大学(国家专项计划)[公办]",
      "majorGroup": "工科试验班(电子工程类)",
      "planCount": 0,
      "minScore": 655,
      "minRank": 2366,
      "avgScore": 655
    },
    {
      "universityCode": "0305",
      "universityName": "电子科技大学(国家专项计划)[公办]",
      "majorGroup": "航空航天类(飞行器控制信息、无人机应用)",
      "planCount": 0,
      "minScore": 653,
      "minRank": 2699,
      "avgScore": 653
    },
    {
      "universityCode": "0305",
      "universityName": "电子科技大学(国家专项计划)[公办]",
      "majorGroup": "电子信息类(电子信息与物理科学复合培养)",
      "planCount": 0,
      "minScore": 652,
      "minRank": 2914,
      "avgScore": 654
    },
    {
      "universityCode": "0305",
      "universityName": "电子科技大学(国家专项计划)[公办]",
      "majorGroup": "电子信息类(智能仪器、智能控制)",
      "planCount": 0,
      "minScore": 651,
      "minRank": 3105,
      "avgScore": 654
    },
    {
      "universityCode": "0305",
      "universityName": "电子科技大学(国家专项计划)[公办]",
      "majorGroup": "数学类(大数据与智能计算、数学及应用、计算科学)",
      "planCount": 0,
      "minScore": 649,
      "minRank": 3513,
      "avgScore": 650
    }
  ],
  "meta": {
    "source": "河北省教育考试院",
    "sourceUrl": "https://gk.hebeea.edu.cn:88/xxcx/xxcxzx/lnwc",
    "publishedAt": "2026-06-25",
    "quality": "official",
    "updatedAt": "2026-06-25T11:17:22.759Z",
    "totalEntries": 1402,
    "universityCount": 185
  }
}